mcp_clickhouse/__init__.py
mcp_clickhouse/chdb_prompt.py
mcp_clickhouse/main.py
mcp_clickhouse/mcp_env.py
mcp_clickhouse/mcp_server.py
iflow_mcp_mcp_clickhouse-0.1.12.dist-info/METADATA
iflow_mcp_mcp_clickhouse-0.1.12.dist-info/WHEEL
iflow_mcp_mcp_clickhouse-0.1.12.dist-info/entry_points.txt
iflow_mcp_mcp_clickhouse-0.1.12.dist-info/licenses/LICENSE
iflow_mcp_mcp_clickhouse-0.1.12.dist-info/RECORD
