Metadata-Version: 2.4
Name: iflow-mcp_mcp-clickhouse
Version: 0.1.12
Summary: An MCP server for ClickHouse.
Project-URL: Home, https://github.com/ClickHouse/mcp-clickhouse
License-Expression: Apache-2.0
License-File: LICENSE
Requires-Python: >=3.10
Requires-Dist: chdb>=3.3.0
Requires-Dist: clickhouse-connect>=0.8.16
Requires-Dist: fastmcp>=2.0.0
Requires-Dist: python-dotenv>=1.0.1
Requires-Dist: truststore>=0.10
Provides-Extra: dev
Requires-Dist: pytest; extra == 'dev'
Requires-Dist: pytest-asyncio; extra == 'dev'
Requires-Dist: ruff; extra == 'dev'
